MANIFEST.in
README.rst
setup.py
monguo/__init__.py
monguo/connection.py
monguo/document.py
monguo/error.py
monguo/field.py
monguo/util.py
monguo/validator.py
monguo.egg-info/PKG-INFO
monguo.egg-info/SOURCES.txt
monguo.egg-info/dependency_links.txt
monguo.egg-info/not-zip-safe
monguo.egg-info/top_level.txt
test/test.py
test/test_connection.py
test/test_document.py
test/test_field.py