Metadata-Version: 1.1
Name: monguo
Version: 0.1.13
Summary: Asynchronous MongoDB ORM for Tornado
Home-page: https://github.com/shiyanhui/monguo
Author: Lime YH.Shi
Author-email: shiyanhui66@gmail.com
License: http://www.apache.org/licenses/LICENSE-2.0
Keywords: monguo,mongo,mongodb,pymongo,gridfs,bson,motor,tornado,ORM,asynchronous
Platform: UNKNOWN
Classifier: Intended Audience :: Developers
Classifier: License :: OSI Approved :: Apache Software License
Classifier: Development Status :: 5 - Production/Stable
Classifier: Natural Language :: English
Classifier: Programming Language :: Python :: 2
Classifier: Programming Language :: Python :: 2.6
Classifier: Programming Language :: Python :: 2.7
Classifier: Programming Language :: Python :: 3
Classifier: Programming Language :: Python :: 3.0
Classifier: Programming Language :: Python :: 3.3
Classifier: Operating System :: MacOS :: MacOS X
Classifier: Operating System :: Unix
Classifier: Programming Language :: Python
Classifier: Programming Language :: Python :: Implementation :: CPython
